pgZhSearch/__init__.py
pgZhSearch/base_search.py
pgZhSearch/create_user.py
pgZhSearch/db_utils.py
pgZhSearch/getshells.py
pgZhSearch/init_import_data_mixin.py
pgZhSearch/treeUtils.py
pgZhSearch/extract_keyword/__init__.py
pgZhSearch/extract_keyword/extract_keyword.py
pgZhSearch/extract_keyword/stopwords.txt
pgZhSearch/extract_keyword/synonym_dict.txt
pgZhSearch/extract_keyword/user_dict.txt
pgZhSearch-0.0.5.dist-info/DESCRIPTION.rst
pgZhSearch-0.0.5.dist-info/METADATA
pgZhSearch-0.0.5.dist-info/RECORD
pgZhSearch-0.0.5.dist-info/WHEEL
pgZhSearch-0.0.5.dist-info/metadata.json
pgZhSearch-0.0.5.dist-info/top_level.txt
