Metadata-Version: 2.0
Name: pgZhSearch
Version: 0.0.5
Summary: django-postgresql-zh-full-text-search
Home-page: https://gitee.com/bode135/pgZhSearch
Author: bode135
Author-email: 2248270222@qq.com
License: UNKNOWN
Platform: UNKNOWN
Classifier: Programming Language :: Python :: 3
Classifier: License :: OSI Approved :: MIT License
Classifier: Operating System :: OS Independent
Requires-Dist: jieba
Requires-Dist: psycopg2-binary (==2.9.1)
